setup.py
sql_disco.egg-info/PKG-INFO
sql_disco.egg-info/SOURCES.txt
sql_disco.egg-info/dependency_links.txt
sql_disco.egg-info/not-zip-safe
sql_disco.egg-info/top_level.txt
sqldisco/__init__.py
sqldisco/job.py
sqldisco/split.py
sqldisco/splitter.py
sqldisco/sqldb_io.py
sqldisco/test/__init__.py