Metadata-Version: 1.0
Name: sql-disco
Version: 0.0.3
Summary: Disco SQL Connector
Home-page: http://www.joneisen.me
Author: Jon Eisen
Author-email: jon.m.eisen@gmail.com.com
License: MIT Licensed
Platform: UNKNOWN
